FunCog/__init__.py
FunCog/setup.py
FunCog-0.0.1.dist-info/METADATA
FunCog-0.0.1.dist-info/WHEEL
FunCog-0.0.1.dist-info/top_level.txt
FunCog-0.0.1.dist-info/RECORD
